README.md
setup.py
nbssh/__init__.py
nbssh/__main__.py
nbssh/config_loader.py
nbssh/test.py
nbssh.egg-info/PKG-INFO
nbssh.egg-info/SOURCES.txt
nbssh.egg-info/dependency_links.txt
nbssh.egg-info/entry_points.txt
nbssh.egg-info/requires.txt
nbssh.egg-info/top_level.txt