Metadata-Version: 1.0
Name: nbssh
Version: 0.6.1
Summary: Quickly SSH into a Netbox device..
Home-page: https://github.com/jonpurdy/nbssh/
Author: Jon Purdy
Author-email: jon+nbssh@jonpurdy.com
License: GNU General Public License v3 (GPLv3)
Platform: UNKNOWN
